{
    "version": "3.9.0",
    "architecture": {
        "32bit": {
            "url": "https://github.com/metafates/mangal/releases/download/v3.9.0/mangal_3.9.0_Windows_i386.zip",
            "bin": [
                "mangal.exe"
            ],
            "hash": "a610f534316ed1ef75c7ffa05afc7c5d9c9832f9014db1897db04964726e08f6"
        },
        "64bit": {
            "url": "https://github.com/metafates/mangal/releases/download/v3.9.0/mangal_3.9.0_Windows_x86_64.zip",
            "bin": [
                "mangal.exe"
            ],
            "hash": "1104c50668a17abcfc16c3e5b85a202450d54f19fe2c9402dfe6bf2ab91a8214"
        }
    },
    "homepage": "https://github.com/metafates/mangal",
    "license": "MIT",
    "description": "The ultimate CLI manga downloader!"
}